numero_nome/__init__.py
numero_nome/processamento.py
numero_nome-0.0.1.dist-info/LICENSE
numero_nome-0.0.1.dist-info/METADATA
numero_nome-0.0.1.dist-info/WHEEL
numero_nome-0.0.1.dist-info/top_level.txt
numero_nome-0.0.1.dist-info/RECORD
