Metadata-Version: 2.1
Name: numero-nome
Version: 0.0.1
Summary: Significa o nome completo pela soma se suas letras, pela numerologia.
Home-page: https://github.com/alan-vieira/numero-nome-package
Author: Alan Vieira
Author-email: alansilvavieira@gmail.com
Requires-Python: >=3.8
License-File: LICENSE
